AUTHORS.rst
CONTRIBUTING.rst
HISTORY.rst
LICENSE
MANIFEST.in
README.rst
setup.cfg
setup.py
docs/Makefile
docs/authors.rst
docs/conf.py
docs/contributing.rst
docs/history.rst
docs/index.rst
docs/installation.rst
docs/make.bat
docs/readme.rst
docs/usage.rst
not_odd/__init__.py
not_odd/cli.py
not_odd/not_odd.py
not_odd.egg-info/PKG-INFO
not_odd.egg-info/SOURCES.txt
not_odd.egg-info/dependency_links.txt
not_odd.egg-info/entry_points.txt
not_odd.egg-info/not-zip-safe
not_odd.egg-info/requires.txt
not_odd.egg-info/top_level.txt
tests/__init__.py
tests/test_not_odd.py